lazyqsar/__init__.py
lazyqsar/agnostic.py
lazyqsar/artifacts/__init__.py
lazyqsar/artifacts/artifact_binary_classifier.py
lazyqsar/assemblers/__init__.py
lazyqsar/assemblers/eclectic_binary_classifier.py
lazyqsar/descriptors/__init__.py
lazyqsar/descriptors/cddd.py
lazyqsar/descriptors/chemeleon.py
lazyqsar/descriptors/morgan.py
lazyqsar/descriptors/rdkit_descriptors.py
lazyqsar/feature_selection/__init__.py
lazyqsar/feature_selection/binary_classification/__init__.py
lazyqsar/feature_selection/binary_classification/fs.py
lazyqsar/feature_selection/binary_classification/mfs.py
lazyqsar/heads/__init__.py
lazyqsar/heads/binary_classification/__init__.py
lazyqsar/heads/binary_classification/et.py
lazyqsar/heads/binary_classification/lr.py
lazyqsar/heads/binary_classification/mlp.py
lazyqsar/heads/binary_classification/svc.py
lazyqsar/latent_variables/__init__.py
lazyqsar/latent_variables/binary_classification/__init__.py
lazyqsar/latent_variables/binary_classification/lv.py
lazyqsar/preprocess/__init__.py
lazyqsar/preprocess/prep.py
lazyqsar/qsar.py
lazyqsar/utils/__init__.py
lazyqsar/utils/_install_extras.py
lazyqsar/utils/deciders.py
lazyqsar/utils/evaluators.py
lazyqsar/utils/io.py
lazyqsar/utils/logging.py
lazyqsar/utils/progress.py
lazyqsar/utils/samplers.py
lazyqsar/utils/setup.py
lazyqsar-2.2.2.dist-info/METADATA
lazyqsar-2.2.2.dist-info/WHEEL
lazyqsar-2.2.2.dist-info/entry_points.txt
lazyqsar-2.2.2.dist-info/licenses/LICENSE
lazyqsar-2.2.2.dist-info/RECORD
