Metadata-Version: 2.4
Name: lazyqsar
Version: 2.2.2
Summary: A library to quickly build QSAR models
License: GPLv3
License-File: LICENSE
Keywords: qsar,machine-learning,chemistry,computer-aided-drug-design
Author: Ersilia Open Source Initiative
Author-email: hello@ersilia.io
Requires-Python: >=3.10
Classifier: Programming Language :: Python :: 3.11
Classifier: Programming Language :: Python :: 3.12
Classifier: License :: OSI Approved :: GNU General Public License v3 (GPLv3)
Classifier: Operating System :: OS Independent
Classifier: Topic :: Scientific/Engineering :: Artificial Intelligence
Provides-Extra: descriptors
Requires-Dist: h5py (==3.14.0)
Requires-Dist: joblib (==1.5.1)
Requires-Dist: loguru (==0.7.3)
Requires-Dist: numpy (==2.1.3)
Requires-Dist: onnxconverter-common (==1.16.0)
Requires-Dist: onnxruntime (==1.20.1)
Requires-Dist: optuna (==4.4.0)
Requires-Dist: pandas (==2.3.0)
Requires-Dist: psutil (==7.0.0)
Requires-Dist: rdkit (==2025.9.1) ; extra == "descriptors"
Requires-Dist: rich (==14.1.0)
Requires-Dist: scikit-learn (==1.6.1)
Requires-Dist: skl2onnx (==1.19.1)
Project-URL: Source Code, https://github.com/ersilia-os/lazy-qsar
